durl/VERSION
durl/__init__.py
durl_py-0.1.1.dist-info/LICENSE
durl_py-0.1.1.dist-info/METADATA
durl_py-0.1.1.dist-info/WHEEL
durl_py-0.1.1.dist-info/RECORD
