Metadata-Version: 2.3
Name: durl-py
Version: 0.1.1
Summary: Simple Data URL Model
License: MIT
Author: Allen Chou
Author-email: f1470891079@gmail.com
Requires-Python: >=3.11,<4
Classifier: License :: OSI Approved :: MIT License
Classifier: Programming Language :: Python :: 3
Classifier: Programming Language :: Python :: 3.11
Classifier: Programming Language :: Python :: 3.12
Classifier: Programming Language :: Python :: 3.13
Requires-Dist: dictpress (>=0.3.0)
Requires-Dist: pydantic (>=2)
Requires-Dist: rich
Requires-Dist: str-or-none
Project-URL: Homepage, https://github.com/allen2c/durl-py
Project-URL: PyPI, https://pypi.org/project/durl-py/
Project-URL: Repository, https://github.com/allen2c/durl-py
